tinyrpc.py
tinytinyrpc-0.0.1.dist-info/DESCRIPTION.rst
tinytinyrpc-0.0.1.dist-info/METADATA
tinytinyrpc-0.0.1.dist-info/RECORD
tinytinyrpc-0.0.1.dist-info/WHEEL
tinytinyrpc-0.0.1.dist-info/metadata.json
tinytinyrpc-0.0.1.dist-info/top_level.txt
