Metadata-Version: 2.0
Name: tinytinyrpc
Version: 0.0.1
Summary: A tiny transport-agnostic RPC implementation
Home-page: http://github.com/rokups/tinyrpc
Author: Rokas Kupstys
Author-email: rokups+tinyrpc@zoho.com
License: MIT
Keywords: rpc
Platform: UNKNOWN
